gceni_testing/__init__.py
gceni_testing/exposure.py
gceni_testing/filter.py
gceni_testing-0.0.1.dist-info/METADATA
gceni_testing-0.0.1.dist-info/WHEEL
gceni_testing-0.0.1.dist-info/top_level.txt
gceni_testing-0.0.1.dist-info/RECORD
