Metadata-Version: 2.1
Name: gceni-testing
Version: 0.0.1
Summary: only for testing purpose
Home-page: https://github.com/Err0rGCeni/DIOProject_Pacote_de_Processamento
Author: GCeni
Author-email: gceni10@gmail.com
Requires-Python: >=3.8
Requires-Dist: scikit-image
